{
    "$schema": "https://schema.management.azure.com/schemas/2019-04-01/deploymentTemplate.json#",
    "contentVersion": "1.0.0.0",
    "parameters": {
        "connections_twitter_name": {
            "defaultValue": "S4MSCTwitter",
            "type": "String"
        },
        "region": {
            "defaultValue": "uksouth",
            "type": "String"
        },
        "tenantId": {
            "defaultValue": "[parameters('region')]",
            "type": "String"
        },
        "clientId": {
            "defaultValue": "[parameters('region')]",
            "type": "String"
        },
        "secret": {
            "defaultValue": "[parameters('region')]",
            "type": "String"
        }
    },
    "variables": {
        "workflows_SearchConnectorSetup_name": "[concat('la-',parameters('connections_twitter_name'),'-setup')]",
        "workflows_SearchConnectorSearch_name": "[concat('la-',parameters('connections_twitter_name'),'-search')]",
        "workflows_SearchConnectorTrigger_name": "[concat('la-',parameters('connections_twitter_name'),'-trigger')]",
        "graphConnectorUrl":"[concat('https://graph.microsoft.com/beta/external/connections/',parameters('connections_twitter_name'),'SearchConnector')]"
    },
    "resources": [
        {
            "type": "Microsoft.Logic/workflows",
            "apiVersion": "2017-07-01",
            "name": "[variables('workflows_SearchConnectorSetup_name')]",
            "location": "[parameters('region')]",
            "properties": {
                "state": "Enabled",
                "definition": {
                    "$schema": "https://schema.management.azure.com/providers/Microsoft.Logic/schemas/2016-06-01/workflowdefinition.json#",
                    "actions": {
                        "Check_TwitterSearchConnector_exists": {
                            "inputs": {
                                "authentication": {
                                    "audience": "https://graph.microsoft.com",
                                    "clientId": "[parameters('clientId')]",
                                    "secret": "[parameters('secret')]",
                                    "tenant": "[parameters('tenantId')]",
                                    "type": "ActiveDirectoryOAuth"
                                },
                                "method": "GET",
                                "uri": "[variables('graphConnectorUrl')]"
                            },
                            "runAfter": {},
                            "type": "Http"
                        },
                        "Check_schema_exists": {
                            "inputs": {
                                "authentication": {
                                    "audience": "https://graph.microsoft.com",
                                    "clientId": "[parameters('clientId')]",
                                    "secret": "[parameters('secret')]",
                                    "tenant": "[parameters('tenantId')]",
                                    "type": "ActiveDirectoryOAuth"
                                },
                                "method": "GET",
                                "uri": "[concat(variables('graphConnectorUrl'),'/schema')]"
                            },
                            "runAfter": {
                                "Create_S4MSC-TwitterSearchConnector_if_doesn't_exist": [
                                    "Succeeded",
                                    "Skipped"
                                ]
                            },
                            "type": "Http"
                        },
                        "Create_S4MSC-TwitterSearchConnector_if_doesn't_exist": {
                            "inputs": {
                                "authentication": {
                                    "audience": "https://graph.microsoft.com",
                                    "clientId": "[parameters('clientId')]",
                                    "secret": "[parameters('secret')]",
                                    "tenant": "[parameters('tenantId')]",
                                    "type": "ActiveDirectoryOAuth"
                                },
                                "body": {
                                    "description": "Connector for showing key tweets",
                                    "id": "[concat(parameters('connections_twitter_name'),'SearchConnector')]",
                                    "name": "Twitter Connector"
                                },
                                "method": "POST",
                                "uri": "https://graph.microsoft.com/beta/external/connections"
                            },
                            "runAfter": {
                                "Check_TwitterSearchConnector_exists": [
                                    "Failed"
                                ]
                            },
                            "type": "Http"
                        },
                        "Create_schema_if_it_doesn't_exists": {
                            "inputs": {
                                "authentication": {
                                    "audience": "https://graph.microsoft.com",
                                    "clientId": "[parameters('clientId')]",
                                    "secret": "[parameters('secret')]",
                                    "tenant": "[parameters('tenantId')]",
                                    "type": "ActiveDirectoryOAuth"
                                },
                                "body": {
                                    "baseType": "microsoft.graph.externalItem",
                                    "properties": [
                                        {
                                            "isQueryable": true,
                                            "isRefinable": false,
                                            "isRetrievable": true,
                                            "isSearchable": true,
                                            "name": "TweetText",
                                            "type": "String"
                                        },
                                        {
                                            "isQueryable": true,
                                            "isRefinable": false,
                                            "isRetrievable": true,
                                            "isSearchable": true,
                                            "name": "TweetId",
                                            "type": "String"
                                        },
                                        {
                                            "isQueryable": true,
                                            "isRefinable": false,
                                            "isRetrievable": true,
                                            "isSearchable": false,
                                            "name": "CreatedAt",
                                            "type": "DateTime"
                                        },
                                        {
                                            "isQueryable": false,
                                            "isRefinable": false,
                                            "isRetrievable": true,
                                            "isSearchable": false,
                                            "name": "RetweetCount",
                                            "type": "Int64"
                                        },
                                        {
                                            "isQueryable": true,
                                            "isRefinable": false,
                                            "isRetrievable": true,
                                            "isSearchable": true,
                                            "name": "TweetedByUserName",
                                            "type": "String"
                                        },
                                        {
                                            "isQueryable": true,
                                            "isRefinable": false,
                                            "isRetrievable": true,
                                            "isSearchable": true,
                                            "name": "TweetByFullName",
                                            "type": "String"
                                        },
                                        {
                                            "isQueryable": true,
                                            "isRefinable": false,
                                            "isRetrievable": true,
                                            "isSearchable": true,
                                            "name": "OriginalTweetUserName",
                                            "type": "String"
                                        },
                                        {
                                            "isQueryable": true,
                                            "isRefinable": false,
                                            "isRetrievable": true,
                                            "isSearchable": true,
                                            "name": "OriginalTweetFullName",
                                            "type": "String"
                                        },
                                        {
                                            "isQueryable": false,
                                            "isRefinable": false,
                                            "isRetrievable": true,
                                            "isSearchable": false,
                                            "name": "ProfileImageUrl",
                                            "type": "String"
                                        }
                                    ]
                                },
                                "method": "POST",
                                "uri": "[concat(variables('graphConnectorUrl'),'/schema')]"
                            },
                            "runAfter": {
                                "Check_schema_exists": [
                                    "Failed"
                                ]
                            },
                            "type": "Http"
                        }
                    },
                    "contentVersion": "1.0.0.0",
                    "outputs": {},
                    "parameters": {},
                    "triggers": {
                        "manual": {
                            "inputs": {
                                "schema": {}
                            },
                            "kind": "Http",
                            "type": "Request"
                        }
                    }
                },
                "parameters": {}
            }
        },
        {
            "type": "Microsoft.Web/connections",
            "apiVersion": "2016-06-01",
            "name": "twitter",
            "location": "[parameters('region')]",
            "kind": "V1",
            "properties": {
                "displayName": "Twitter",
                "statuses": [
                    {
                        "status": "Connected"
                    }
                ],
                "customParameterValues": {},
                "api": {
                    "name": "twitter",
                    "displayName": "Twitter",
                    "description": "Twitter is an online social networking service that enables users to send and receive short messages called 'tweets'. Connect to Twitter to manage your tweets. You can perform various actions such as send tweet, search, view followers, etc.",
                    "iconUri": "[concat('https://connectoricons-prod.azureedge.net/releases/v1.0.1473/1.0.1473.2431/twitter/icon.png')]",
                    "brandColor": "#5fa9dd",
                    "id": "[concat('/subscriptions/',subscription().subscriptionId,'/providers/Microsoft.Web/locations/',parameters('region'),'/managedApis/twitter')]",
                    "type": "Microsoft.Web/locations/managedApis"
                },
                "testLinks": []
            }
        },
        {
            "type": "Microsoft.Logic/workflows",
            "apiVersion": "2017-07-01",
            "name": "[variables('workflows_SearchConnectorSearch_name')]",
            "location": "[parameters('region')]",
            "dependsOn": [
                "[resourceId('Microsoft.Web/connections', 'twitter')]"
            ],
            "properties": {
                "state": "Enabled",
                "definition": {
                    "$schema": "https://schema.management.azure.com/providers/Microsoft.Logic/schemas/2016-06-01/workflowdefinition.json#",
                    "contentVersion": "1.0.0.0",
                    "parameters": {
                        "$connections": {
                            "defaultValue": {},
                            "type": "Object"
                        }
                    },
                    "triggers": {
                        "manual": {
                            "type": "Request",
                            "kind": "Http",
                            "inputs": {
                                "schema": {}
                            }
                        }
                    },
                    "actions": {
                        "For_each": {
                            "foreach": "@body('Search_tweets')",
                            "actions": {
                                "HTTP": {
                                    "runAfter": {},
                                    "type": "Http",
                                    "inputs": {
                                        "authentication": {
                                            "audience": "https://graph.microsoft.com",
                                            "clientId": "[parameters('clientId')]",
                                            "secret": "[parameters('secret')]",
                                            "tenant": "[parameters('tenantId')]",
                                            "type": "ActiveDirectoryOAuth"
                                        },
                                        "body": {
                                            "acl": [
                                                {
                                                    "accessType": "grant",
                                                    "identitySource": "azureActiveDirectory",
                                                    "type": "everyone",
                                                    "value": ""
                                                }
                                            ],
                                            "content": {
                                                "type": "text",
                                                "value": "@{items('For_each')['TweetText']}"
                                            },
                                            "properties": {
                                                "TweetByFullName": "@{items('For_each')?['UserDetails']?['FullName']}",
                                                "TweetId": "@{items('For_each')?['TweetId']}",
                                                "TweetText": "@{items('For_each')['TweetText']}",
                                                "TweetedByUserName": "@{items('For_each')?['UserDetails']?['FullName']}"
                                            },
                                            "type": "microsoft.graph.externalItem"
                                        },
                                        "method": "PUT",
                                        "uri": "[concat(variables('graphConnectorUrl'),'/items/@{items(''For_each'')?[''TweetId'']}')]"
                                    }
                                }
                            },
                            "runAfter": {
                                "Search_tweets": [
                                    "Succeeded"
                                ]
                            },
                            "type": "Foreach"
                        },
                        "Search_tweets": {
                            "runAfter": {},
                            "type": "ApiConnection",
                            "inputs": {
                                "host": {
                                    "connection": {
                                        "name": "@parameters('$connections')['twitter']['connectionId']"
                                    }
                                },
                                "method": "get",
                                "path": "/searchtweets",
                                "queries": {
                                    "maxResults": 99,
                                    "searchQuery": "#CollabTalk"
                                }
                            }
                        }
                    },
                    "outputs": {}
                },
                "parameters": {
                    "$connections": {
                        "value": {
                            "twitter": {
                                "connectionId": "[resourceId('Microsoft.Web/connections', 'twitter')]",
                                "connectionName": "twitter",
                                "id": "/subscriptions/[subscription().subscriptionId]/providers/Microsoft.Web/locations/[parameters('region')]/managedApis/twitter"
                            }
                        }
                    }
                }
            }
        },
        {
            "type": "Microsoft.Logic/workflows",
            "apiVersion": "2017-07-01",
            "name": "[variables('workflows_SearchConnectorTrigger_name')]",
            "location": "[parameters('region')]",
            "dependsOn": [
                "[resourceId('Microsoft.Web/connections', 'twitter')]"
            ],
            "properties": {
                "state": "Enabled",
                "definition": {
                    "$schema": "https://schema.management.azure.com/providers/Microsoft.Logic/schemas/2016-06-01/workflowdefinition.json#",
                    "contentVersion": "1.0.0.0",
                    "parameters": {
                        "$connections": {
                            "defaultValue": {},
                            "type": "Object"
                        }
                    },
                    "triggers": {
                        "When_a_Collabtalk_tweet_is_posted": {
                            "recurrence": {
                                "frequency": "Day",
                                "interval": 1
                            },
                            "splitOn": "@triggerBody()?['value']",
                            "type": "ApiConnection",
                            "inputs": {
                                "host": {
                                    "connection": {
                                        "name": "@parameters('$connections')['twitter']['connectionId']"
                                    }
                                },
                                "method": "get",
                                "path": "/onnewtweet",
                                "queries": {
                                    "searchQuery": "#MicrosoftSearch"
                                }
                            }
                        }
                    },
                    "actions": {
                        "HTTP": {
                            "runAfter": {},
                            "type": "Http",
                            "inputs": {
                                "authentication": {
                                    "audience": "https://graph.microsoft.com",
                                    "clientId": "[parameters('clientId')]",
                                    "secret": "[parameters('secret')]",
                                    "tenant": "[parameters('tenantId')]",
                                    "type": "ActiveDirectoryOAuth"
                                },
                                "body": {
                                    "acl": [
                                        {
                                            "accessType": "grant",
                                            "identitySource": "azureActiveDirectory",
                                            "type": "everyone",
                                            "value": "43c5e796-f484-4157-8c93-73ac8b1cf7bf"
                                        }
                                    ],
                                    "content": {
                                        "type": "text",
                                        "value": "@{triggerBody()?['TweetText']}"
                                    },
                                    "properties": {
                                        "TweetByFullName": "@{triggerBody()?['UserDetails']?['FullName']}",
                                        "TweetId": "@{triggerBody()?['TweetId']}",
                                        "TweetText": "@{triggerBody()?['TweetText']}",
                                        "TweetedByUserName": "@{triggerBody()?['UserDetails']?['UserName']}"
                                    },
                                    "type": "microsoft.graph.externalItem"
                                },
                                "method": "PUT",
                                "uri": "[concat(variables('graphConnectorUrl'),'/items/@{triggerBody()?[''TweetId'']}')]"
                            }
                        }
                    },
                    "outputs": {}
                },
                "parameters": {
                    "$connections": {
                        "value": {
                            "twitter": {
                                "connectionId": "[resourceId('Microsoft.Web/connections','twitter')]",
                                "connectionName": "twitter",
                                "id": "/subscriptions/[subscription().subscriptionId]/providers/Microsoft.Web/locations/[parameters('region')]/managedApis/twitter"
                            }
                        }
                    }
                }
            }
        }
    ]
}